serprog/__init__.py
serprog/__main__.py
serprog/bootprotocol.py
serprog/business.py
serprog/cmdline.py
serprog/device.py
serprog/exceptions.py
serprog/ihex.py
serprog/loader.py
serprog-0.1.2.dist-info/LICENSE
serprog-0.1.2.dist-info/METADATA
serprog-0.1.2.dist-info/WHEEL
serprog-0.1.2.dist-info/entry_points.txt
serprog-0.1.2.dist-info/top_level.txt
serprog-0.1.2.dist-info/RECORD
