Metadata-Version: 2.1
Name: serprog
Version: 0.1.2
Summary: A serial and secure programming tool for microcontroller.
Home-page: https://github.com/cy023/SerProg
Author: cy023
Author-email: cyyang023@gmail.com
License: MIT
License-File: LICENSE
Requires-Dist: progressbar2
Requires-Dist: pyserial
Requires-Dist: setuptools
